calm_cache/__init__.py
calm_cache/contrib.py
calm_cache/backends/__init__.py
calm_cache/backends/calmcache.py
calm_cache/backends/memcached.py
calm_cache/decorators/__init__.py
calm_cache/decorators/response_cache.py
django3_calm_cache-1.0.2.dist-info/LICENSE
django3_calm_cache-1.0.2.dist-info/METADATA
django3_calm_cache-1.0.2.dist-info/WHEEL
django3_calm_cache-1.0.2.dist-info/top_level.txt
django3_calm_cache-1.0.2.dist-info/RECORD
