Metadata-Version: 2.1
Name: django3-calm-cache
Version: 1.0.2
Summary: A set of useful tools that enhance the standard Django cache experience
Home-page: https://github.com/ramwin/django-calm-cache
Author: Xiang Wang
Author-email: ramwin@qq.com
License: BSD 3-Clause
Keywords: django cache memcache memcached minting pylibmc libmemcached
Platform: Platform Independent
Classifier: Development Status :: 4 - Beta
Classifier: Environment :: Web Environment
Classifier: Framework :: Django
Classifier: Intended Audience :: Developers
Classifier: License :: OSI Approved :: BSD License
Classifier: Topic :: Internet :: WWW/HTTP
Classifier: Topic :: Internet :: WWW/HTTP :: Dynamic Content
Classifier: Topic :: Software Development :: Libraries :: Python Modules
Classifier: Operating System :: OS Independent
Classifier: Programming Language :: Python
Classifier: Programming Language :: Python :: 3.6
License-File: LICENSE
